onnx_donut/__init__.py
onnx_donut/exporter.py
onnx_donut/predictor.py
onnx_donut/quantizer.py
onnx_donut-0.1.0.dist-info/LICENSE
onnx_donut-0.1.0.dist-info/METADATA
onnx_donut-0.1.0.dist-info/WHEEL
onnx_donut-0.1.0.dist-info/top_level.txt
onnx_donut-0.1.0.dist-info/RECORD
