Metadata-Version: 2.1
Name: onnx-donut
Version: 0.1.0
Summary: Export Donut model to onnx and run it with onnxruntime
Author-email: Ambroise Berthe <ambroise.berthe@ikomia.ai>
Keywords: donut,onnx
Classifier: Programming Language :: Python :: 3
Requires-Python: >=3.9
License-File: LICENSE
Requires-Dist: transformers <=4.35.0,>=4.25.1
Requires-Dist: torch <3.0.0
Requires-Dist: torchvision <1.0.0
Requires-Dist: timm ==0.5.4
Requires-Dist: donut-python ==1.0.9
Requires-Dist: onnx <2.0.0
Requires-Dist: onnxruntime <2.0.0
Requires-Dist: protobuf <3.21.0
